{
  "login":
     {
      "usuario": "05942138788",
      "senha": "Mudar@123"
     },
  "recoverPassword": 
     {
      "email": "sidraque@toodoo.com",
      "cpf": "11111111111",
      "dataNascimento": "15/01/2000"
     },
  "register":
  [
    {
      
      "id": 1,
      "cpf": "11111111111",
      "dataNascimento": "01/01/2000",
      "email": "email@email.com",
      "senha": "123456"
    },
    
    {
      "cpf": "22222222222",
      "dataNascimento": "02/02/2000",
      "email": "email2@email2.com",
      "senha": "1234567"
    }
    
  ]
}
